[
  {
    "fileName": "Important Circular.pdf",
    "pages": "1",
    "copies": "9",
    "type": "color",
    "price": "45",
    "date": "2026-03-28T11:15:03.602Z"
  },
  {
    "fileName": "SIGNATURE.pdf",
    "pages": "1",
    "copies": "1",
    "type": "bw",
    "price": "2",
    "date": "2026-03-28T11:17:22.734Z"
  },
  {
    "fileName": "financemanagement.pdf",
    "pages": "3",
    "copies": "5",
    "type": "bw",
    "price": "30",
    "date": "2026-03-28T11:23:06.275Z"
  },
  {
    "fileName": "KRISHNADHASRHINI.L.pdf",
    "pages": "4",
    "copies": "1",
    "type": "bw",
    "price": "8",
    "date": "2026-03-28T11:33:26.367Z"
  },
  {
    "fileName": "KRISHNADHARSHINI (1).pdf",
    "pages": "2",
    "copies": "6",
    "type": "bw",
    "price": "24",
    "date": "2026-03-28T11:44:01.964Z"
  },
  {
    "fileName": "KRISHNADHASRHINI.L.pdf",
    "pages": "4",
    "copies": "1",
    "type": "color",
    "price": "15",
    "date": "2026-03-28T12:06:31.451Z"
  },
  {
    "fileName": "KRISHNADHARSHINI (1).pdf",
    "pages": "2",
    "copies": "1",
    "type": "bw",
    "price": "2",
    "date": "2026-03-28T12:08:03.212Z"
  },
  {
    "fileName": "sachin's updated resume.pdf",
    "pages": "1",
    "copies": "3",
    "type": "color",
    "price": "15",
    "date": "2026-03-28T12:49:36.130Z"
  },
  {
    "fileName": "pan back.pdf",
    "pages": "1",
    "copies": "1",
    "type": "bw",
    "price": "2",
    "date": "2026-03-28T13:15:49.885Z"
  }
]